{
	"info": {
		"_postman_id": "72b57782-1d14-4afd-9a18-9e0831806861",
		"name": "VAS API",
		"schema": "https://schema.getpostman.com/json/collection/v2.1.0/collection.json",
		"_exporter_id": "5582195"
	},
	"item": [
		{
			"name": "1 Get Catalogue",
			"request": {
				"method": "GET",
				"header": [
					{
						"key": "x-ibm-client-id",
						"value": "<YOUR CLIENT ID>",
						"type": "text",
						"description": "The client ID you received when creating the app on the portal."
					},
					{
						"key": "x-ibm-client-secret",
						"value": "<YOUR CLIENT SECRET>",
						"type": "text",
						"description": "The client secret you received when creating the app on the portal."
					}
				],
				"url": {
					"raw": "https://b2b-api.nedbank.co.za/apimarket/b2b-sb/nb-vas/catalogue?categoryID=<CATEGORY ID>",
					"protocol": "https",
					"host": [
						"b2b-api",
						"nedbank",
						"co",
						"za"
					],
					"path": [
						"apimarket",
						"b2b-sb",
						"nb-vas",
						"catalogue"
					],
					"query": [
						{
							"key": "categoryID",
							"value": "<CATEGORY ID>",
							"description": "It is an optional Parameter.Based on provided categoryID we can retrieve the ProductID of each catalogue."
						}
					]
				}
			},
			"response": [
				{
					"name": "sample response",
					"originalRequest": {
						"method": "GET",
						"header": [
							{
								"key": "x-ibm-client-id",
								"value": "<YOUR CLIENT ID>",
								"type": "text",
								"description": "The client ID you received when creating the app on the portal."
							},
							{
								"key": "x-ibm-client-secret",
								"value": "<YOUR CLIENT SECRET>",
								"type": "text",
								"description": "The client secret you received when creating the app on the portal."
							}
						],
						"url": {
							"raw": "https://b2b-api.nedbank.co.za/apimarket/b2b-sb/nb-vas/catalogue",
							"protocol": "https",
							"host": [
								"b2b-api",
								"nedbank",
								"co",
								"za"
							],
							"path": [
								"apimarket",
								"b2b-sb",
								"nb-vas",
								"catalogue"
							]
						}
					},
					"_postman_previewlanguage": "json",
					"header": [],
					"cookie": [],
					"body": "{\r\n    \"ProductTypes\": [\r\n        {\r\n            \"ProductCategories\": [],\r\n            \"ID\": \"11329\",\r\n            \"Code\": \"VC\",\r\n            \"WebIcon\": \"https://www.nedbank.co.za/content/dam/vas/web/Vouchers.svg\",\r\n            \"IOSIcon\": \"https://www.nedbank.co.za/content/dam/vas/ios/Vouchers.png\",\r\n            \"AndroidIcon\": \"https://www.nedbank.co.za/content/dam/vas/android/Vouchers.png\",\r\n            \"Description\": \"Buy gift voucher\",\r\n            \"ProductCount\": 164,\r\n            \"AdditionalContent\": \"Buy gift voucher\"\r\n        },\r\n        {\r\n            \"ProductCategories\": [],\r\n            \"ID\": \"11339\",\r\n            \"Code\": \"PP\",\r\n            \"WebIcon\": \"https://www.nedbank.co.za/content/dam/vas/web/Prepaid.svg\",\r\n            \"IOSIcon\": \"https://www.nedbank.co.za/content/dam/vas/ios/Prepaid.png\",\r\n            \"AndroidIcon\": \"https://www.nedbank.co.za/content/dam/vas/android/Prepaid.png\",\r\n            \"Description\": \"Buy Prepaid data, airtime or SMSs\",\r\n            \"ProductCount\": 295,\r\n            \"AdditionalContent\": \"Buy Prepaid data, airtime or SMSs\"\r\n        },\r\n        {\r\n            \"ProductCategories\": [],\r\n            \"ID\": \"11342\",\r\n            \"Code\": \"LOTTO\",\r\n            \"WebIcon\": \"https://www.nedbank.co.za/content/dam/vas/web/Lotto.svg\",\r\n            \"IOSIcon\": \"https://www.nedbank.co.za/content/dam/vas/ios/Lotto.png\",\r\n            \"AndroidIcon\": \"https://www.nedbank.co.za/content/dam/vas/android/Lotto.png\",\r\n            \"Description\": \"Play LOTTO or PowerBall\",\r\n            \"ProductCount\": 0,\r\n            \"AdditionalContent\": \"Play LOTTO or PowerBall\"\r\n        }\r\n    ],\r\n    \"ErrorCode\": 0,\r\n    \"ErrorDescription\": \"OK\",\r\n    \"TxID\": \"f1508a8b-678a-4e89-8d09-f5bea77d0eca\"\r\n}"
				}
			]
		},
		{
			"name": "2 Get Balance",
			"request": {
				"method": "GET",
				"header": [
					{
						"key": "x-ibm-client-id",
						"value": "<YOUR CLIENT ID>",
						"type": "text"
					},
					{
						"key": "x-ibm-client-secret",
						"value": "<YOUR CLIENT SECRET>",
						"type": "text"
					}
				],
				"url": {
					"raw": "https://b2b-api.nedbank.co.za/apimarket/b2b-sb/nb-vas/balance",
					"protocol": "https",
					"host": [
						"b2b-api",
						"nedbank",
						"co",
						"za"
					],
					"path": [
						"apimarket",
						"b2b-sb",
						"nb-vas",
						"balance"
					]
				}
			},
			"response": [
				{
					"name": "sample response",
					"originalRequest": {
						"method": "GET",
						"header": [
							{
								"key": "x-ibm-client-id",
								"value": "<YOUR CLIENT ID>",
								"type": "text"
							},
							{
								"key": "x-ibm-client-secret",
								"value": "<YOUR CLIENT SECRET>",
								"type": "text"
							}
						],
						"url": {
							"raw": "https://b2b-api.nedbank.co.za/apimarket/b2b-sb/nb-vas/balance",
							"protocol": "https",
							"host": [
								"b2b-api",
								"nedbank",
								"co",
								"za"
							],
							"path": [
								"apimarket",
								"b2b-sb",
								"nb-vas",
								"balance"
							]
						}
					},
					"_postman_previewlanguage": "json",
					"header": [
						{
							"key": "Content-Type",
							"value": "application/json",
							"name": "Content-Type",
							"description": "",
							"type": "text"
						}
					],
					"cookie": [],
					"body": "{\n    \"AccountId\": \"1234567891\",\n    \"Amount\": {\n        \"Amount\": 25845.12,\n        \"Currency\": \"ZAR\"\n    },\n    \"CreditDebitIndicator\": \"Credit\",\n    \"Type\": \"InterimAvailable\"\n}"
				}
			]
		},
		{
			"name": "3 Purchase Prepaid",
			"request": {
				"method": "POST",
				"header": [
					{
						"key": "x-ibm-client-id",
						"value": "<YOUR CLIENT ID>\t",
						"type": "text",
						"description": "The client ID you received when creating the app on the portal."
					},
					{
						"key": "x-ibm-client-secret",
						"value": "<YOUR CLIENT SECRET>",
						"type": "text",
						"description": "The client secret you received when creating the app on the portal."
					}
				],
				"body": {
					"mode": "raw",
					"raw": "{\r\n  \"ProductID\": \"1ce7081d-c681-4811-19e6-08d7f5a6abf1\",\r\n  \"Amount\": 40,\r\n  \"Quantity\": 1,\r\n  \"Reference\": \"Test\",\r\n  \"MobileNumber\":\"0612345678\"\r\n}\r\n",
					"options": {
						"raw": {
							"language": "json"
						}
					}
				},
				"url": {
					"raw": "https://b2b-api.nedbank.co.za/apimarket/b2b-sb/nb-vas/prepaid/purchase",
					"protocol": "https",
					"host": [
						"b2b-api",
						"nedbank",
						"co",
						"za"
					],
					"path": [
						"apimarket",
						"b2b-sb",
						"nb-vas",
						"prepaid",
						"purchase"
					]
				}
			},
			"response": [
				{
					"name": "sample response",
					"originalRequest": {
						"method": "POST",
						"header": [
							{
								"key": "x-ibm-client-id",
								"value": "<YOUR CLIENT ID>",
								"type": "text",
								"description": "The client ID you received when creating the app on the portal."
							},
							{
								"key": "x-ibm-client-secret",
								"value": "<YOUR CLIENT SECRET>",
								"type": "text",
								"description": "The client secret you received when creating the app on the portal."
							}
						],
						"body": {
							"mode": "raw",
							"raw": "{\r\n  \"ProductID\": \"1ce7081d-c681-4811-19e6-08d7f5a6abf1\",\r\n  \"Amount\": 40,\r\n  \"Quantity\": 1,\r\n  \"Reference\": \"Test\",\r\n  \"MobileNumber\":\"0612345678\"\r\n}\r\n",
							"options": {
								"raw": {
									"language": "json"
								}
							}
						},
						"url": {
							"raw": "https://b2b-api.nedbank.co.za/apimarket/b2b-sb/nb-vas/prepaid/purchase",
							"protocol": "https",
							"host": [
								"b2b-api",
								"nedbank",
								"co",
								"za"
							],
							"path": [
								"apimarket",
								"b2b-sb",
								"nb-vas",
								"prepaid",
								"purchase"
							]
						}
					},
					"_postman_previewlanguage": "json",
					"header": [],
					"cookie": [],
					"body": "{\r\n    \"RequestID\": \"834fd7ba-9bf7-4ff5-83c3-75f75816746e\",\r\n    \"OrderID\": \"c0289d54-6c3f-4099-0aa9-08d92bbb4a11\",\r\n    \"ReferenceNumber\": \"20210616/Nedbank/489133779101\",\r\n    \"OrderStatus\": \"SUCCESS\",\r\n    \"OrderRequestedDate\": \"2021-06-16\",\r\n    \"Result\": {\r\n        \"Status\": \"SUCCESS\",\r\n        \"Code\": \"R000\",\r\n        \"Description\": \"SUCCESS\"\r\n    }\r\n}"
				}
			]
		},
		{
			"name": "4 Purchase Voucher",
			"request": {
				"method": "POST",
				"header": [
					{
						"key": "x-ibm-client-id",
						"value": "<YOUR CLIENT ID>",
						"type": "text",
						"description": "The client ID you received when creating the app on the portal."
					},
					{
						"key": "x-ibm-client-secret",
						"value": "<YOUR CLIENT SECRET>",
						"type": "text",
						"description": "The client secret you received when creating the app on the portal."
					}
				],
				"body": {
					"mode": "raw",
					"raw": "{\r\n  \"ProductID\": \"b7610988-de0e-4810-02d0-08d9250f5d47\",\r\n  \"Amount\": 500,\r\n  \"Quantity\": 1,\r\n  \"Reference\": \"APIM\"\r\n}\r\n",
					"options": {
						"raw": {
							"language": "json"
						}
					}
				},
				"url": {
					"raw": "https://b2b-api.nedbank.co.za/apimarket/b2b-sb/nb-vas/vouchers/purchase",
					"protocol": "https",
					"host": [
						"b2b-api",
						"nedbank",
						"co",
						"za"
					],
					"path": [
						"apimarket",
						"b2b-sb",
						"nb-vas",
						"vouchers",
						"purchase"
					]
				}
			},
			"response": [
				{
					"name": "sample response",
					"originalRequest": {
						"method": "POST",
						"header": [
							{
								"key": "x-ibm-client-id",
								"value": "<YOUR CLIENT ID>",
								"type": "text",
								"description": "The client ID you received when creating the app on the portal."
							},
							{
								"key": "x-ibm-client-secret",
								"value": "<YOUR CLIENT SECRET>",
								"type": "text",
								"description": "The client secret you received when creating the app on the portal."
							}
						],
						"body": {
							"mode": "raw",
							"raw": "{\r\n  \"ProductID\": \"b7610988-de0e-4810-02d0-08d9250f5d47\",\r\n  \"Amount\": 500,\r\n  \"Quantity\": 1,\r\n  \"Reference\": \"APIM\"\r\n}\r\n",
							"options": {
								"raw": {
									"language": "json"
								}
							}
						},
						"url": {
							"raw": "https://b2b-api.nedbank.co.za/apimarket/b2b-sb/nb-vas/vouchers/purchase",
							"protocol": "https",
							"host": [
								"b2b-api",
								"nedbank",
								"co",
								"za"
							],
							"path": [
								"apimarket",
								"b2b-sb",
								"nb-vas",
								"vouchers",
								"purchase"
							]
						}
					},
					"_postman_previewlanguage": "json",
					"header": [],
					"cookie": [],
					"body": "{\r\n    \"RequestID\": \"c4e3aae2-bb48-49fc-be65-d993b9aeb364\",\r\n    \"OrderID\": \"34b1d628-8805-4510-6a93-08d92ede6e5c\",\r\n    \"ReferenceNumber\": \"20210616/Nedbank/489133779104\",\r\n    \"OrderStatus\": \"SUCCESS\",\r\n    \"OrderRequestedDate\": \"2021-06-16\",\r\n    \"Tokens\": [\r\n        {\r\n            \"Key\": \"Vendor Reference Number\",\r\n            \"Value\": \"1113380279610620\"\r\n        },\r\n        {\r\n            \"Key\": \"Serial Number\",\r\n            \"Value\": \"20210616175456291275\"\r\n        }\r\n    ],\r\n    \"Result\": {\r\n        \"Status\": \"SUCCESS\",\r\n        \"Code\": \"R000\",\r\n        \"Description\": \"SUCCESS\"\r\n    }\r\n}"
				}
			]
		}
	],
	"event": [
		{
			"listen": "prerequest",
			"script": {
				"type": "text/javascript",
				"exec": [
					""
				]
			}
		},
		{
			"listen": "test",
			"script": {
				"type": "text/javascript",
				"exec": [
					""
				]
			}
		}
	],
	"variable": [
		{
			"key": "BaseURI",
			"value": "https://b2b-api.nedbank.co.za/apimarket/b2b-sb/nb-vas"
		},
		{
			"key": "client_id",
			"value": "40f1c907-eab3-4e4d-bdf5-7b757b532f55"
		},
		{
			"key": "client_secret",
			"value": "xJ4cU1lT0nC1sA1sX8fS2aP5aW6iC1iV5bU3bW7bD5yE5xJ6tC"
		},
		{
			"key": "categoryID",
			"value": "11339"
		},
		{
			"key": "categoryI_D",
			"value": "11329"
		}
	]
}